pyvulncheck/__init__.py
pyvulncheck-0.1.0.dist-info/LICENSE
pyvulncheck-0.1.0.dist-info/WHEEL
pyvulncheck-0.1.0.dist-info/METADATA
pyvulncheck-0.1.0.dist-info/RECORD
